wowless/cli.py
wowless_cli-0.0.12.dist-info/LICENSE
wowless_cli-0.0.12.dist-info/METADATA
wowless_cli-0.0.12.dist-info/WHEEL
wowless_cli-0.0.12.dist-info/entry_points.txt
wowless_cli-0.0.12.dist-info/top_level.txt
wowless_cli-0.0.12.dist-info/RECORD
