Metadata-Version: 2.1
Name: wowless-cli
Version: 0.0.12
Summary: CLI for wowless
Home-page: https://github.com/wowless-dev/cli
Author: Ferronn
Author-email: ferronn@ferronn.dev
License: MIT
Project-URL: Bug Tracker, https://github.com/wowless-dev/cli/issues
Platform: UNKNOWN
Classifier: License :: OSI Approved :: MIT License
Classifier: Operating System :: OS Independent
Classifier: Programming Language :: Python :: 3
Classifier: Programming Language :: Python :: 3 :: Only
Classifier: Programming Language :: Python :: 3.6
Classifier: Programming Language :: Python :: 3.7
Classifier: Programming Language :: Python :: 3.8
Classifier: Programming Language :: Python :: 3.9
Classifier: Programming Language :: Python :: 3.10
Requires-Python: >=3.6
License-File: LICENSE
Requires-Dist: click
Requires-Dist: progress
Requires-Dist: requests
